streamlit_audio_stream_player/__init__.py
streamlit_audio_stream_player/frontend/components.json
streamlit_audio_stream_player/frontend/index.html
streamlit_audio_stream_player/frontend/package.json
streamlit_audio_stream_player/frontend/postcss.config.js
streamlit_audio_stream_player/frontend/tailwind.config.js
streamlit_audio_stream_player/frontend/tsconfig.json
streamlit_audio_stream_player/frontend/tsconfig.node.json
streamlit_audio_stream_player/frontend/vite.config.ts
streamlit_audio_stream_player/frontend/build/index.html
streamlit_audio_stream_player/frontend/build/static/css/index.css
streamlit_audio_stream_player/frontend/build/static/js/index.js
streamlit_audio_stream_player/frontend/src/BarVisualizerComponent.tsx
streamlit_audio_stream_player/frontend/src/index.css
streamlit_audio_stream_player/frontend/src/index.tsx
streamlit_audio_stream_player/frontend/src/components/visualizers/bar-visualizer.tsx
streamlit_audio_stream_player/frontend/src/components/visualizers/orb-visualizer.tsx
streamlit_audio_stream_player/frontend/src/hooks/use-audio-analysis.ts
streamlit_audio_stream_player/frontend/src/hooks/use-bar-animator.ts
streamlit_audio_stream_player/frontend/src/types/index.ts
streamlit_audio_stream_player-0.2.2.dist-info/licenses/LICENSE
streamlit_audio_stream_player-0.2.2.dist-info/METADATA
streamlit_audio_stream_player-0.2.2.dist-info/WHEEL
streamlit_audio_stream_player-0.2.2.dist-info/top_level.txt
streamlit_audio_stream_player-0.2.2.dist-info/RECORD
