Metadata-Version: 2.4
Name: streamlit-audio-stream-player
Version: 0.2.2
Summary: Beautiful audio stream player component for Streamlit with frequency visualization and state animations
Home-page: https://github.com/bensonbs/streamlit-audio-stream-player
Author: Benson Sung
Author-email: Benson Sung <benson.bs.sung@gmail.com>
License: MIT
Project-URL: Homepage, https://github.com/bensonbs/streamlit-audio-stream-player
Project-URL: Repository, https://github.com/bensonbs/streamlit-audio-stream-player
Project-URL: Issues, https://github.com/bensonbs/streamlit-audio-stream-player/issues
Keywords: streamlit,audio,visualizer,frequency,component
Requires-Python: >=3.8
License-File: LICENSE
Requires-Dist: streamlit>=1.0.0
Dynamic: author
Dynamic: home-page
Dynamic: license-file
Dynamic: requires-python
